{
  "title": "《包容》冬天过恩尼不再需要我 - 岁韩见柏松.jpg",
  "description": "",
  "imageViews": "0",
  "creationTime": {
    "timestamp": "1688605393",
    "formatted": "2023年7月6日 UTC 01:03:13"
  },
  "photoTakenTime": {
    "timestamp": "1648283882",
    "formatted": "2022年3月26日 UTC 08:38:02"
  },
  "geoData": {
    "latitude": 0.0,
    "longitude": 0.0,
    "altitude": 0.0,
    "latitudeSpan": 0.0,
    "longitudeSpan": 0.0
  },
  "geoDataExif": {
    "latitude": 0.0,
    "longitude": 0.0,
    "altitude": 0.0,
    "latitudeSpan": 0.0,
    "longitudeSpan": 0.0
  },
  "url": "https://lh3.googleusercontent.com/oAB6Ys1ZQAeAnkJ7LnEq61fFHwz-yvyxzKtdA8n1GGqbkXKab_2Fr7AFqw4Hbzxs_UIuZVw08n4Z-SVj-NsTd7DrCNlREAUZB9oK6Qhm",
  "googlePhotosOrigin": {
    "mobileUpload": {
      "deviceFolder": {
        "localFolderName": ""
      },
      "deviceType": "ANDROID_PHONE"
    }
  }
}