{
  "title": "海外大秦孝公姜太公陈祯禄公爵Cendol---明修蜀道成都至昆明开车.jpg",
  "description": "",
  "imageViews": "0",
  "creationTime": {
    "timestamp": "1685957744",
    "formatted": "2023年6月5日 UTC 09:35:44"
  },
  "photoTakenTime": {
    "timestamp": "1667547111",
    "formatted": "2022年11月4日 UTC 07:31:51"
  },
  "geoData": {
    "latitude": 0.0,
    "longitude": 0.0,
    "altitude": 0.0,
    "latitudeSpan": 0.0,
    "longitudeSpan": 0.0
  },
  "geoDataExif": {
    "latitude": 0.0,
    "longitude": 0.0,
    "altitude": 0.0,
    "latitudeSpan": 0.0,
    "longitudeSpan": 0.0
  },
  "people": [{
    "name": "Joey Chua"
  }],
  "url": "https://lh3.googleusercontent.com/O74vQm5aj7lyFOPuv9sxpHoz9n5LLFPsjb_O6Ujp3Sb8m6PIjKPaNm90JpcrgnqYs3AZKRUfSUIdhsUb3yef6LoBOyrzYbSZGtspwoGv",
  "googlePhotosOrigin": {
    "mobileUpload": {
      "deviceFolder": {
        "localFolderName": "Bluetooth"
      },
      "deviceType": "ANDROID_PHONE"
    }
  }
}