{
  "title": "IMG_20221017_184017.jpg",
  "description": "",
  "imageViews": "0",
  "creationTime": {
    "timestamp": "1680619015",
    "formatted": "2023年4月4日 UTC 14:36:55"
  },
  "photoTakenTime": {
    "timestamp": "1678172273",
    "formatted": "2023年3月7日 UTC 06:57:53"
  },
  "geoData": {
    "latitude": 0.0,
    "longitude": 0.0,
    "altitude": 0.0,
    "latitudeSpan": 0.0,
    "longitudeSpan": 0.0
  },
  "geoDataExif": {
    "latitude": 0.0,
    "longitude": 0.0,
    "altitude": 0.0,
    "latitudeSpan": 0.0,
    "longitudeSpan": 0.0
  },
  "people": [{
    "name": "Joey Chua"
  }],
  "url": "https://lh3.googleusercontent.com/_PoxmXix3-PJ6H3IXTAW2e-rFyb7fyPtxinRmQ_Jn4QhalITAZgxpkRKgqtLBx-rtYbqmJ2WhHip99yrP8nCrJR9XnDVbGqKbTgmWI-f",
  "googlePhotosOrigin": {
    "mobileUpload": {
      "deviceFolder": {
        "localFolderName": "Bluetooth"
      },
      "deviceType": "ANDROID_PHONE"
    }
  }
}