{
  "title": "00712xT8ly1gv35xivu7yj621r32gnpf02.jpg",
  "description": "",
  "imageViews": "4",
  "creationTime": {
    "timestamp": "1633341460",
    "formatted": "2021年10月4日 UTC 09:57:40"
  },
  "photoTakenTime": {
    "timestamp": "1633333570",
    "formatted": "2021年10月4日 UTC 07:46:10"
  },
  "geoData": {
    "latitude": 0.0,
    "longitude": 0.0,
    "altitude": 0.0,
    "latitudeSpan": 0.0,
    "longitudeSpan": 0.0
  },
  "geoDataExif": {
    "latitude": 0.0,
    "longitude": 0.0,
    "altitude": 0.0,
    "latitudeSpan": 0.0,
    "longitudeSpan": 0.0
  },
  "url": "https://lh3.googleusercontent.com/7qv0RXp7mlgMxpAW3cT6hTLj7zYr3zVf4Z6Lfo1ptM48aGoFL9glIax-Qp8cLcwn95f612-tSxuSi8uMaKNehkp6wvQTgyS2YdTfKQip",
  "googlePhotosOrigin": {
    "mobileUpload": {
      "deviceFolder": {
        "localFolderName": "Bluetooth"
      },
      "deviceType": "ANDROID_PHONE"
    }
  }
}