{
  "title": "FB_IMG_1626858567451.jpg",
  "description": "",
  "imageViews": "7",
  "creationTime": {
    "timestamp": "1626953784",
    "formatted": "2021年7月22日 UTC 11:36:24"
  },
  "photoTakenTime": {
    "timestamp": "1626858567",
    "formatted": "2021年7月21日 UTC 09:09:27"
  },
  "geoData": {
    "latitude": 0.0,
    "longitude": 0.0,
    "altitude": 0.0,
    "latitudeSpan": 0.0,
    "longitudeSpan": 0.0
  },
  "geoDataExif": {
    "latitude": 0.0,
    "longitude": 0.0,
    "altitude": 0.0,
    "latitudeSpan": 0.0,
    "longitudeSpan": 0.0
  },
  "url": "https://lh3.googleusercontent.com/_KflVE3VDM3mOBrl39X2z7RmXNQ17YZIrVrKkotTzmITM64iywjSanDAI2lYoMZjfe-RL3xj3opwOfvJH0a-Yd1Kp1CHdPrfU5ITr-jd",
  "googlePhotosOrigin": {
    "mobileUpload": {
      "deviceFolder": {
        "localFolderName": ""
      },
      "deviceType": "ANDROID_PHONE"
    }
  }
}