{
  "title": "flower garden - world largest 2.jpeg",
  "description": "",
  "imageViews": "10",
  "creationTime": {
    "timestamp": "1632145504",
    "formatted": "2021年9月20日 UTC 13:45:04"
  },
  "photoTakenTime": {
    "timestamp": "1632143084",
    "formatted": "2021年9月20日 UTC 13:04:44"
  },
  "geoData": {
    "latitude": 0.0,
    "longitude": 0.0,
    "altitude": 0.0,
    "latitudeSpan": 0.0,
    "longitudeSpan": 0.0
  },
  "geoDataExif": {
    "latitude": 0.0,
    "longitude": 0.0,
    "altitude": 0.0,
    "latitudeSpan": 0.0,
    "longitudeSpan": 0.0
  },
  "url": "https://lh3.googleusercontent.com/LgOeyD6DwTO9ajPtYwEGAo3vUfeTVJdGxi6rSrRcZPW11lGn6HwBFIM6eWWevtHeLDRx4stfFh4ytV7EJXxliZwjWW_HeidoiyM673bB",
  "googlePhotosOrigin": {
    "mobileUpload": {
      "deviceFolder": {
        "localFolderName": ""
      },
      "deviceType": "ANDROID_PHONE"
    }
  }
}