{
  "title": "img-163204224410875eb6912c168c545a72ce90b126d7560.jpg",
  "description": "",
  "imageViews": "4",
  "creationTime": {
    "timestamp": "1632059242",
    "formatted": "2021年9月19日 UTC 13:47:22"
  },
  "photoTakenTime": {
    "timestamp": "1632042244",
    "formatted": "2021年9月19日 UTC 09:04:04"
  },
  "geoData": {
    "latitude": 0.0,
    "longitude": 0.0,
    "altitude": 0.0,
    "latitudeSpan": 0.0,
    "longitudeSpan": 0.0
  },
  "geoDataExif": {
    "latitude": 0.0,
    "longitude": 0.0,
    "altitude": 0.0,
    "latitudeSpan": 0.0,
    "longitudeSpan": 0.0
  },
  "url": "https://lh3.googleusercontent.com/J-epCw3ckJU7sjrNsojMw1z3KgDNlzaNAA0t8BgrOPYObtGrHfxq22KIKdpQG63hrIWYR0CGBNpKNoWTptYmz8eOLnGrGXRs38dDTffR",
  "googlePhotosOrigin": {
    "mobileUpload": {
      "deviceFolder": {
        "localFolderName": "weibo"
      },
      "deviceType": "ANDROID_PHONE"
    }
  }
}