{
  "title": "IMG-20210110-WA0000.jpg",
  "description": "",
  "imageViews": "6",
  "creationTime": {
    "timestamp": "1610430599",
    "formatted": "2021年1月12日 UTC 05:49:59"
  },
  "photoTakenTime": {
    "timestamp": "1610246227",
    "formatted": "2021年1月10日 UTC 02:37:07"
  },
  "geoData": {
    "latitude": 0.0,
    "longitude": 0.0,
    "altitude": 0.0,
    "latitudeSpan": 0.0,
    "longitudeSpan": 0.0
  },
  "geoDataExif": {
    "latitude": 0.0,
    "longitude": 0.0,
    "altitude": 0.0,
    "latitudeSpan": 0.0,
    "longitudeSpan": 0.0
  },
  "url": "https://lh3.googleusercontent.com/qUAK4QD4yMB94iEAsQCR8X4YMus_8R-aCeAr2z5alqi1c4sAo3rwz-ZYkmyzlfo1h2o4BHX1uv9aK-O-bmDTPd7LL9wCMpQntG2ogdoN",
  "googlePhotosOrigin": {
    "mobileUpload": {
      "deviceFolder": {
        "localFolderName": "Sent"
      },
      "deviceType": "ANDROID_PHONE"
    }
  }
}