{
  "title": "img-16349127137356b69b1148a28ad2ca9714987e61a0ead.jpg",
  "description": "",
  "imageViews": "5",
  "creationTime": {
    "timestamp": "1634920047",
    "formatted": "2021年10月22日 UTC 16:27:27"
  },
  "photoTakenTime": {
    "timestamp": "1634912713",
    "formatted": "2021年10月22日 UTC 14:25:13"
  },
  "geoData": {
    "latitude": 0.0,
    "longitude": 0.0,
    "altitude": 0.0,
    "latitudeSpan": 0.0,
    "longitudeSpan": 0.0
  },
  "geoDataExif": {
    "latitude": 0.0,
    "longitude": 0.0,
    "altitude": 0.0,
    "latitudeSpan": 0.0,
    "longitudeSpan": 0.0
  },
  "url": "https://lh3.googleusercontent.com/dZizGEdj_6VVwssxRl--DSujO5Pc5nhIasq3ctp4ui2RW4vZVUpXlEycJlpcwlUNgn1xmka04IxuPNRncijDQisaJiWJJwLht01KaKis",
  "googlePhotosOrigin": {
    "mobileUpload": {
      "deviceFolder": {
        "localFolderName": "weibo"
      },
      "deviceType": "ANDROID_PHONE"
    }
  }
}