{
  "title": "IMG-20210926-WA0005.jpeg",
  "description": "",
  "imageViews": "5",
  "creationTime": {
    "timestamp": "1632665137",
    "formatted": "2021年9月26日 UTC 14:05:37"
  },
  "photoTakenTime": {
    "timestamp": "1632665511",
    "formatted": "2021年9月26日 UTC 14:11:51"
  },
  "geoData": {
    "latitude": 0.0,
    "longitude": 0.0,
    "altitude": 0.0,
    "latitudeSpan": 0.0,
    "longitudeSpan": 0.0
  },
  "geoDataExif": {
    "latitude": 0.0,
    "longitude": 0.0,
    "altitude": 0.0,
    "latitudeSpan": 0.0,
    "longitudeSpan": 0.0
  },
  "url": "https://lh3.googleusercontent.com/znUxl3uOp7NhRmpYAGs4dBRZRehdESRAyBOFqQK3gBu52Wft617d4KyD4VsefSuuT1zkwe-Oon4P7f9PDqg2mVcNRxP5CPTtSAhU0EF-",
  "googlePhotosOrigin": {
    "mobileUpload": {
      "deviceFolder": {
        "localFolderName": "WhatsApp Business Images"
      },
      "deviceType": "ANDROID_PHONE"
    }
  }
}