{
  "title": "IMG_20211204_150245.jpg",
  "description": "",
  "imageViews": "5",
  "creationTime": {
    "timestamp": "1638765509",
    "formatted": "2021年12月6日 UTC 04:38:29"
  },
  "photoTakenTime": {
    "timestamp": "1638597765",
    "formatted": "2021年12月4日 UTC 06:02:45"
  },
  "geoData": {
    "latitude": 3.424493,
    "longitude": 101.179357,
    "altitude": -0.987,
    "latitudeSpan": 0.0,
    "longitudeSpan": 0.0
  },
  "geoDataExif": {
    "latitude": 3.424493,
    "longitude": 101.179357,
    "altitude": -0.987,
    "latitudeSpan": 0.0,
    "longitudeSpan": 0.0
  },
  "url": "https://lh3.googleusercontent.com/GL0yvKQB6KQezm5nrzz3C_PBobxEcjl0Rtzv7-zfNeoyHPyuWEJxYT70EgOOOJq1WnWpVP9jaO7h2pDB2i4TmBpMgKbmY9kQE22BpBM3",
  "googlePhotosOrigin": {
    "mobileUpload": {
      "deviceFolder": {
        "localFolderName": "Bluetooth"
      },
      "deviceType": "ANDROID_PHONE"
    }
  }
}