{
  "title": "IMG_20210312_231417.jpg",
  "description": "",
  "imageViews": "4",
  "creationTime": {
    "timestamp": "1615569737",
    "formatted": "2021年3月12日 UTC 17:22:17"
  },
  "photoTakenTime": {
    "timestamp": "1615557684",
    "formatted": "2021年3月12日 UTC 14:01:24"
  },
  "geoData": {
    "latitude": 0.0,
    "longitude": 0.0,
    "altitude": 0.0,
    "latitudeSpan": 0.0,
    "longitudeSpan": 0.0
  },
  "geoDataExif": {
    "latitude": 0.0,
    "longitude": 0.0,
    "altitude": 0.0,
    "latitudeSpan": 0.0,
    "longitudeSpan": 0.0
  },
  "url": "https://lh3.googleusercontent.com/0Vo_yCF-dajU4D3LB8BOIXYCWW0MLghPr5cM6Bfh5cfk1ieiwbbEsFJ61xIHvZB960balGnf7jHcavZJAo6E56y9QTAOGjdvGqFt_z3f",
  "googlePhotosOrigin": {
    "mobileUpload": {
      "deviceFolder": {
        "localFolderName": ""
      },
      "deviceType": "ANDROID_PHONE"
    }
  }
}