{
  "title": "Screenshot_2021-04-18-16-33-27-35.jpg",
  "description": "",
  "imageViews": "3",
  "creationTime": {
    "timestamp": "1626589105",
    "formatted": "2021年7月18日 UTC 06:18:25"
  },
  "photoTakenTime": {
    "timestamp": "1618731207",
    "formatted": "2021年4月18日 UTC 07:33:27"
  },
  "geoData": {
    "latitude": 0.0,
    "longitude": 0.0,
    "altitude": 0.0,
    "latitudeSpan": 0.0,
    "longitudeSpan": 0.0
  },
  "geoDataExif": {
    "latitude": 0.0,
    "longitude": 0.0,
    "altitude": 0.0,
    "latitudeSpan": 0.0,
    "longitudeSpan": 0.0
  },
  "url": "https://lh3.googleusercontent.com/moO5fl4O47nBeDwkA2-lbjiWswK-Uk8JVanTQgUzgtqx9rK_1doSE4LyCwoad3uWOzVJUVIX25wWjWWOluvc4yiy0aJ9GiMmkb250fRG",
  "googlePhotosOrigin": {
    "mobileUpload": {
      "deviceFolder": {
        "localFolderName": ""
      },
      "deviceType": "ANDROID_PHONE"
    }
  }
}