{
  "title": "1609591_629391630463060_591606030_n.jpg",
  "description": "",
  "imageViews": "50",
  "creationTime": {
    "timestamp": "1410498964",
    "formatted": "2014年9月12日 UTC 05:16:04"
  },
  "photoTakenTime": {
    "timestamp": "1410498641",
    "formatted": "2014年9月12日 UTC 05:10:41"
  },
  "geoData": {
    "latitude": 0.0,
    "longitude": 0.0,
    "altitude": 0.0,
    "latitudeSpan": 0.0,
    "longitudeSpan": 0.0
  },
  "geoDataExif": {
    "latitude": 0.0,
    "longitude": 0.0,
    "altitude": 0.0,
    "latitudeSpan": 0.0,
    "longitudeSpan": 0.0
  },
  "url": "https://lh3.googleusercontent.com/VRZlCPqKMNW6i-CEfvcbuOxJTI5yEAUOaUQ8PYzwXkjmuAJjn-PHOqtQ2gTYp5DFQnnahPksdu0Nl4JsoAcDYOzfONTMQgo00ZrY92c",
  "googlePhotosOrigin": {
    "mobileUpload": {
      "deviceType": "ANDROID_PHONE"
    }
  }
}