{
  "title": "35fc64ee91c668e808a92089748260d217848551.jpeg",
  "description": "",
  "imageViews": "69",
  "creationTime": {
    "timestamp": "1406445914",
    "formatted": "2014年7月27日 UTC 07:25:14"
  },
  "photoTakenTime": {
    "timestamp": "1406445914",
    "formatted": "2014年7月27日 UTC 07:25:14"
  },
  "geoData": {
    "latitude": 0.0,
    "longitude": 0.0,
    "altitude": 0.0,
    "latitudeSpan": 0.0,
    "longitudeSpan": 0.0
  },
  "geoDataExif": {
    "latitude": 0.0,
    "longitude": 0.0,
    "altitude": 0.0,
    "latitudeSpan": 0.0,
    "longitudeSpan": 0.0
  },
  "url": "https://lh3.googleusercontent.com/qdMrUo0Wu4evq0gxCk7eweTe_wwg-9hBur75iAZ3aiNANtN77WUP4ZNoVK-ZQVkRw2-IGgEml_M0ziXRP4GhXAvPsvgevOLa1X-m85Y",
  "googlePhotosOrigin": {
    "mobileUpload": {
      "deviceType": "ANDROID_PHONE"
    }
  }
}