{
  "title": "IMG_46113943764862.jpeg",
  "description": "",
  "imageViews": "69",
  "creationTime": {
    "timestamp": "1405039715",
    "formatted": "2014年7月11日 UTC 00:48:35"
  },
  "photoTakenTime": {
    "timestamp": "1405038480",
    "formatted": "2014年7月11日 UTC 00:28:00"
  },
  "geoData": {
    "latitude": 0.0,
    "longitude": 0.0,
    "altitude": 0.0,
    "latitudeSpan": 0.0,
    "longitudeSpan": 0.0
  },
  "geoDataExif": {
    "latitude": 0.0,
    "longitude": 0.0,
    "altitude": 0.0,
    "latitudeSpan": 0.0,
    "longitudeSpan": 0.0
  },
  "url": "https://lh3.googleusercontent.com/nX-CnGILH8d91skg2afSSo_JWEWS-0HO1RkZov7LDW7J-aqwusWQkJXt92kobDe4IYa20VQuSTu0Nhlr_3j5mcQKabHDB9bgiOEH51c",
  "googlePhotosOrigin": {
    "mobileUpload": {
      "deviceType": "ANDROID_PHONE"
    }
  }
}