{
  "title": "Screenshot_2017-08-13-05-06-06.png",
  "description": "",
  "imageViews": "27",
  "creationTime": {
    "timestamp": "1502775867",
    "formatted": "2017年8月15日 UTC 05:44:27"
  },
  "photoTakenTime": {
    "timestamp": "1502568366",
    "formatted": "2017年8月12日 UTC 20:06:06"
  },
  "geoData": {
    "latitude": 0.0,
    "longitude": 0.0,
    "altitude": 0.0,
    "latitudeSpan": 0.0,
    "longitudeSpan": 0.0
  },
  "geoDataExif": {
    "latitude": 0.0,
    "longitude": 0.0,
    "altitude": 0.0,
    "latitudeSpan": 0.0,
    "longitudeSpan": 0.0
  },
  "url": "https://lh3.googleusercontent.com/2o63eCh2DHs262mPNQy_1j2absZfFDSjeevnCqqrkSGT3kQrfd2mxlPsYF258AUD3Bh4E0hA53kIAN6X4fEvxXMCnfGISMhrLLhYnSQg",
  "googlePhotosOrigin": {
    "mobileUpload": {
      "deviceFolder": {
        "localFolderName": ""
      },
      "deviceType": "ANDROID_PHONE"
    }
  }
}