{
  "title": "18550003q73no263r2o4.jpg",
  "description": "",
  "imageViews": "5",
  "creationTime": {
    "timestamp": "1608751834",
    "formatted": "2020年12月23日 UTC 19:30:34"
  },
  "photoTakenTime": {
    "timestamp": "1608727696",
    "formatted": "2020年12月23日 UTC 12:48:16"
  },
  "geoData": {
    "latitude": 0.0,
    "longitude": 0.0,
    "altitude": 0.0,
    "latitudeSpan": 0.0,
    "longitudeSpan": 0.0
  },
  "geoDataExif": {
    "latitude": 0.0,
    "longitude": 0.0,
    "altitude": 0.0,
    "latitudeSpan": 0.0,
    "longitudeSpan": 0.0
  },
  "people": [{
    "name": "Joey Chua"
  }],
  "url": "https://lh3.googleusercontent.com/HUKfQPzobGqkdtPNwirY1uZq8HSgNP9jl_WIzgXjGJWNy4Le-0eBp8cyXHeitRom1720oOUMayOIUWwysUdCsiK0xOYl2eiBjFXV44PC",
  "googlePhotosOrigin": {
    "mobileUpload": {
      "deviceFolder": {
        "localFolderName": ""
      },
      "deviceType": "ANDROID_PHONE"
    }
  }
}