{
  "title": "18nr00018rsr86n048on.jpg",
  "description": "",
  "imageViews": "4",
  "creationTime": {
    "timestamp": "1608751825",
    "formatted": "2020年12月23日 UTC 19:30:25"
  },
  "photoTakenTime": {
    "timestamp": "1608727660",
    "formatted": "2020年12月23日 UTC 12:47:40"
  },
  "geoData": {
    "latitude": 0.0,
    "longitude": 0.0,
    "altitude": 0.0,
    "latitudeSpan": 0.0,
    "longitudeSpan": 0.0
  },
  "geoDataExif": {
    "latitude": 0.0,
    "longitude": 0.0,
    "altitude": 0.0,
    "latitudeSpan": 0.0,
    "longitudeSpan": 0.0
  },
  "people": [{
    "name": "Joey Chua"
  }],
  "url": "https://lh3.googleusercontent.com/0MEm6BtziEkLTyIeCcxY2Vc9Dbf4HTUGlQ69MH0vZBoAihkYpLhy3xnusGg7Eb3XuMkdhOq9IxmZptLpPEXeJVaQ1FkX2-AaqWgvx4iG",
  "googlePhotosOrigin": {
    "mobileUpload": {
      "deviceFolder": {
        "localFolderName": ""
      },
      "deviceType": "ANDROID_PHONE"
    }
  }
}