{
  "title": "e84b3bb7d865bbd06c8e29b8ffb2a031.jpeg",
  "description": "",
  "imageViews": "6",
  "creationTime": {
    "timestamp": "1608092385",
    "formatted": "2020年12月16日 UTC 04:19:45"
  },
  "photoTakenTime": {
    "timestamp": "1608029974",
    "formatted": "2020年12月15日 UTC 10:59:34"
  },
  "geoData": {
    "latitude": 0.0,
    "longitude": 0.0,
    "altitude": 0.0,
    "latitudeSpan": 0.0,
    "longitudeSpan": 0.0
  },
  "geoDataExif": {
    "latitude": 0.0,
    "longitude": 0.0,
    "altitude": 0.0,
    "latitudeSpan": 0.0,
    "longitudeSpan": 0.0
  },
  "url": "https://lh3.googleusercontent.com/2JIG9KPLSptzayj1MOC5M1Zq_ZsMM6O5WMVfeC-T_6LxIhV-o6fU1pl_DDKkawAyDA5F4YC6bfK_qAB2ARAM8FZk2LSJ_MdULUm349jN",
  "googlePhotosOrigin": {
    "mobileUpload": {
      "deviceFolder": {
        "localFolderName": ""
      },
      "deviceType": "ANDROID_PHONE"
    }
  }
}