{
  "title": "FB_IMG_1607959433087.jpg",
  "description": "",
  "imageViews": "7",
  "creationTime": {
    "timestamp": "1608092338",
    "formatted": "2020年12月16日 UTC 04:18:58"
  },
  "photoTakenTime": {
    "timestamp": "1607959433",
    "formatted": "2020年12月14日 UTC 15:23:53"
  },
  "geoData": {
    "latitude": 0.0,
    "longitude": 0.0,
    "altitude": 0.0,
    "latitudeSpan": 0.0,
    "longitudeSpan": 0.0
  },
  "geoDataExif": {
    "latitude": 0.0,
    "longitude": 0.0,
    "altitude": 0.0,
    "latitudeSpan": 0.0,
    "longitudeSpan": 0.0
  },
  "url": "https://lh3.googleusercontent.com/X91nXjZhjZVdWv-cEvkrzKKtX2mj2NRNWMRrfFh94mzzNejCRj-d21rX6UdvGg9XPsEUlj8vbto5Qm134MiDALzR3uuy3rdVWFf1BxBN",
  "googlePhotosOrigin": {
    "mobileUpload": {
      "deviceFolder": {
        "localFolderName": ""
      },
      "deviceType": "ANDROID_PHONE"
    }
  }
}