{
  "title": "premium-trading.jpg",
  "description": "",
  "imageViews": "7",
  "creationTime": {
    "timestamp": "1600602248",
    "formatted": "2020年9月20日 UTC 11:44:08"
  },
  "photoTakenTime": {
    "timestamp": "1600589395",
    "formatted": "2020年9月20日 UTC 08:09:55"
  },
  "geoData": {
    "latitude": 0.0,
    "longitude": 0.0,
    "altitude": 0.0,
    "latitudeSpan": 0.0,
    "longitudeSpan": 0.0
  },
  "geoDataExif": {
    "latitude": 0.0,
    "longitude": 0.0,
    "altitude": 0.0,
    "latitudeSpan": 0.0,
    "longitudeSpan": 0.0
  },
  "url": "https://lh3.googleusercontent.com/KgOgy_5LYsqTN2MEsVB7LaLebxKMg8Cdd3AbF7i8IdoqRs-c2AFqRp76FJ03mC4N6s95ngO5G3ND-1krRUH-US2w23QDFos97mM8u2d9",
  "googlePhotosOrigin": {
    "mobileUpload": {
      "deviceFolder": {
        "localFolderName": ""
      },
      "deviceType": "ANDROID_PHONE"
    }
  }
}