{
  "title": "Screenshot_2020-12-17-22-09-03-57.jpg",
  "description": "",
  "imageViews": "6",
  "creationTime": {
    "timestamp": "1608250485",
    "formatted": "2020年12月18日 UTC 00:14:45"
  },
  "photoTakenTime": {
    "timestamp": "1608210543",
    "formatted": "2020年12月17日 UTC 13:09:03"
  },
  "geoData": {
    "latitude": 0.0,
    "longitude": 0.0,
    "altitude": 0.0,
    "latitudeSpan": 0.0,
    "longitudeSpan": 0.0
  },
  "geoDataExif": {
    "latitude": 0.0,
    "longitude": 0.0,
    "altitude": 0.0,
    "latitudeSpan": 0.0,
    "longitudeSpan": 0.0
  },
  "people": [{
    "name": "Joey Chua"
  }],
  "url": "https://lh3.googleusercontent.com/8Vf2xheOayjcDTDfkPUvp0UpdXZOKAatFKApts9bLwaR3HX9TEg0hsYQRbm0c0FUS5pqJG3E93jc2axyO71_TWVL-IEqnCpcdFwhlSfI",
  "googlePhotosOrigin": {
    "mobileUpload": {
      "deviceFolder": {
        "localFolderName": ""
      },
      "deviceType": "ANDROID_PHONE"
    }
  }
}