{
  "title": "高颜值11.jpeg",
  "description": "",
  "imageViews": "5",
  "creationTime": {
    "timestamp": "1608187796",
    "formatted": "2020年12月17日 UTC 06:49:56"
  },
  "photoTakenTime": {
    "timestamp": "1608134120",
    "formatted": "2020年12月16日 UTC 15:55:20"
  },
  "geoData": {
    "latitude": 0.0,
    "longitude": 0.0,
    "altitude": 0.0,
    "latitudeSpan": 0.0,
    "longitudeSpan": 0.0
  },
  "geoDataExif": {
    "latitude": 0.0,
    "longitude": 0.0,
    "altitude": 0.0,
    "latitudeSpan": 0.0,
    "longitudeSpan": 0.0
  },
  "url": "https://lh3.googleusercontent.com/IsrSQwO5_coq01WM4XIRTE3XDN9kPmG_dw9ymOPC9BBLG2XJo73nNJxNwajhTACsfIjgdi-pkTdEZPH2BxmryVb5lQ2V-W94wEftZQxD",
  "googlePhotosOrigin": {
    "mobileUpload": {
      "deviceFolder": {
        "localFolderName": ""
      },
      "deviceType": "ANDROID_PHONE"
    }
  }
}