{
  "title": "高颜值5.jpeg",
  "description": "",
  "imageViews": "5",
  "creationTime": {
    "timestamp": "1608187807",
    "formatted": "2020年12月17日 UTC 06:50:07"
  },
  "photoTakenTime": {
    "timestamp": "1608134133",
    "formatted": "2020年12月16日 UTC 15:55:33"
  },
  "geoData": {
    "latitude": 0.0,
    "longitude": 0.0,
    "altitude": 0.0,
    "latitudeSpan": 0.0,
    "longitudeSpan": 0.0
  },
  "geoDataExif": {
    "latitude": 0.0,
    "longitude": 0.0,
    "altitude": 0.0,
    "latitudeSpan": 0.0,
    "longitudeSpan": 0.0
  },
  "url": "https://lh3.googleusercontent.com/-XsOQJ0M2BjFrhwijDVnRDWd0nkqTQIm9aLK8Paz7wkxcO5nPdDr7R9rW3nWmQCJdJ2TtoEnenGaWb3qANRRPNlXnpY74FfvqctTaaaQ",
  "googlePhotosOrigin": {
    "mobileUpload": {
      "deviceFolder": {
        "localFolderName": ""
      },
      "deviceType": "ANDROID_PHONE"
    }
  }
}