{
  "title": "20160801_015052.jpg",
  "description": "",
  "imageViews": "36",
  "creationTime": {
    "timestamp": "1469984075",
    "formatted": "2016年7月31日 UTC 16:54:35"
  },
  "photoTakenTime": {
    "timestamp": "1469983852",
    "formatted": "2016年7月31日 UTC 16:50:52"
  },
  "geoData": {
    "latitude": 0.0,
    "longitude": 0.0,
    "altitude": 0.0,
    "latitudeSpan": 0.0,
    "longitudeSpan": 0.0
  },
  "geoDataExif": {
    "latitude": 0.0,
    "longitude": 0.0,
    "altitude": 0.0,
    "latitudeSpan": 0.0,
    "longitudeSpan": 0.0
  },
  "url": "https://lh3.googleusercontent.com/qC6E7lKqg3dxVWYCOQx4_b_twmvgXl1XboFcqy7rigSjdqTRSwzE2nhWiwIYvitD0lSnqFl_hJaFjBUX8_unEP3oxy8HZOOUN-B5Br0O",
  "googlePhotosOrigin": {
    "driveSync": {
    }
  }
}