{
  "title": "Capture.JPG",
  "description": "",
  "imageViews": "32",
  "creationTime": {
    "timestamp": "1454335932",
    "formatted": "2016年2月1日 UTC 14:12:12"
  },
  "photoTakenTime": {
    "timestamp": "1454339522",
    "formatted": "2016年2月1日 UTC 15:12:02"
  },
  "geoData": {
    "latitude": 0.0,
    "longitude": 0.0,
    "altitude": 0.0,
    "latitudeSpan": 0.0,
    "longitudeSpan": 0.0
  },
  "geoDataExif": {
    "latitude": 0.0,
    "longitude": 0.0,
    "altitude": 0.0,
    "latitudeSpan": 0.0,
    "longitudeSpan": 0.0
  },
  "url": "https://lh3.googleusercontent.com/CJxqZMg2sj-t71XGcq4Z7Zxs-Jf6aKZ0aWIxQE35SORRYnLoCi337mfp_cjzzI5GV8oRtAqXAG5EYFDK4dXpWD37u5SAV_WXzPwX9z5i",
  "googlePhotosOrigin": {
    "photosDesktopUploader": {
    }
  }
}