{
  "title": "IMG-20160209-WA0000.jpg",
  "description": "",
  "imageViews": "26",
  "creationTime": {
    "timestamp": "1455033905",
    "formatted": "2016年2月9日 UTC 16:05:05"
  },
  "photoTakenTime": {
    "timestamp": "1455007588",
    "formatted": "2016年2月9日 UTC 08:46:28"
  },
  "geoData": {
    "latitude": 0.0,
    "longitude": 0.0,
    "altitude": 0.0,
    "latitudeSpan": 0.0,
    "longitudeSpan": 0.0
  },
  "geoDataExif": {
    "latitude": 0.0,
    "longitude": 0.0,
    "altitude": 0.0,
    "latitudeSpan": 0.0,
    "longitudeSpan": 0.0
  },
  "url": "https://lh3.googleusercontent.com/UEikYPvIIllz03rQ8yWI5NHdJRo-7KvHIdvX970ypnDu9QchSg6op6rVoMtJw4sN0bFdo6jReWoZOGkh1wcrTPO4kC9BHR-_YENMHvZb",
  "googlePhotosOrigin": {
    "mobileUpload": {
      "deviceFolder": {
        "localFolderName": "WhatsApp Images"
      },
      "deviceType": "ANDROID_PHONE"
    }
  }
}