{
  "title": "IMG-20160704-WA0001.jpg",
  "description": "",
  "imageViews": "29",
  "creationTime": {
    "timestamp": "1467590188",
    "formatted": "2016年7月3日 UTC 23:56:28"
  },
  "photoTakenTime": {
    "timestamp": "1467587905",
    "formatted": "2016年7月3日 UTC 23:18:25"
  },
  "geoData": {
    "latitude": 0.0,
    "longitude": 0.0,
    "altitude": 0.0,
    "latitudeSpan": 0.0,
    "longitudeSpan": 0.0
  },
  "geoDataExif": {
    "latitude": 0.0,
    "longitude": 0.0,
    "altitude": 0.0,
    "latitudeSpan": 0.0,
    "longitudeSpan": 0.0
  },
  "url": "https://lh3.googleusercontent.com/J7OXxPBfh2aF6ZWoNYYn3qpCD1tEjXWsNcMRwo9cFYw81-yom92s_1yqr3tZ_6nyWpUS5e3vSO1hdVvwpjlt27nVqbsYIxrQ7yrDbexs",
  "googlePhotosOrigin": {
    "mobileUpload": {
      "deviceFolder": {
        "localFolderName": "WhatsApp Images"
      },
      "deviceType": "ANDROID_PHONE"
    }
  }
}