{
  "title": "IMG_20160820_102049.jpg",
  "description": "",
  "imageViews": "29",
  "creationTime": {
    "timestamp": "1471765964",
    "formatted": "2016年8月21日 UTC 07:52:44"
  },
  "photoTakenTime": {
    "timestamp": "1471656051",
    "formatted": "2016年8月20日 UTC 01:20:51"
  },
  "geoData": {
    "latitude": 0.0,
    "longitude": 0.0,
    "altitude": 0.0,
    "latitudeSpan": 0.0,
    "longitudeSpan": 0.0
  },
  "geoDataExif": {
    "latitude": 0.0,
    "longitude": 0.0,
    "altitude": 0.0,
    "latitudeSpan": 0.0,
    "longitudeSpan": 0.0
  },
  "people": [{
    "name": "Ryo Eng"
  }],
  "url": "https://lh3.googleusercontent.com/E_Vi1hAFTphZncInvw99dqGoUICELVZjfsTP4EXSQ_V5Jh4ONc6kPP6VF_yLTlC6FokPpuYP02IiAS4ztjeo-o-7VTpSLEdikFLX2s4V",
  "googlePhotosOrigin": {
    "mobileUpload": {
      "deviceFolder": {
        "localFolderName": "Instagram"
      },
      "deviceType": "ANDROID_PHONE"
    }
  }
}