{
  "title": "10248801_731806496842444_1407864375_n.jpg",
  "description": "",
  "imageViews": "8",
  "creationTime": {
    "timestamp": "1533913183",
    "formatted": "2018年8月10日 UTC 14:59:43"
  },
  "photoTakenTime": {
    "timestamp": "1533889456",
    "formatted": "2018年8月10日 UTC 08:24:16"
  },
  "geoData": {
    "latitude": 0.0,
    "longitude": 0.0,
    "altitude": 0.0,
    "latitudeSpan": 0.0,
    "longitudeSpan": 0.0
  },
  "geoDataExif": {
    "latitude": 0.0,
    "longitude": 0.0,
    "altitude": 0.0,
    "latitudeSpan": 0.0,
    "longitudeSpan": 0.0
  },
  "url": "https://lh3.googleusercontent.com/VNv4GCffe24n_GEpGV8XNoZqTv_aEbbZnY6W61TOE8eTCRDPcJKuqrfeoMVQ5i6a0woDdV0ox4Y3PiaM-wBYOzLspZAnK8-IU1aGKFSi",
  "googlePhotosOrigin": {
    "mobileUpload": {
      "deviceFolder": {
        "localFolderName": ""
      },
      "deviceType": "ANDROID_PHONE"
    }
  }
}