{
  "title": "DSC_0005.JPG",
  "description": "",
  "imageViews": "23",
  "creationTime": {
    "timestamp": "1523671488",
    "formatted": "2018年4月14日 UTC 02:04:48"
  },
  "photoTakenTime": {
    "timestamp": "1523678872",
    "formatted": "2018年4月14日 UTC 04:07:52"
  },
  "geoData": {
    "latitude": 10.6075191,
    "longitude": 103.52148439999999,
    "altitude": 4.294967288E9,
    "latitudeSpan": 0.0,
    "longitudeSpan": 0.0
  },
  "geoDataExif": {
    "latitude": 10.6075191,
    "longitude": 103.52148439999999,
    "altitude": 4.294967288E9,
    "latitudeSpan": 0.0,
    "longitudeSpan": 0.0
  },
  "url": "https://lh3.googleusercontent.com/QmPLcmYX0L1iCu-8HUGmrSuk9_86pa0YU50_bwzN0mXVZOyo2WRBiAyKsAmXKdnHT9--kHLyVQ-EEzbZObt61bHqbgDqzZX8X3zut-Ve",
  "googlePhotosOrigin": {
    "mobileUpload": {
      "deviceFolder": {
        "localFolderName": ""
      },
      "deviceType": "ANDROID_PHONE"
    }
  }
}