{
  "title": "DSC_0003.JPG",
  "description": "",
  "imageViews": "26",
  "creationTime": {
    "timestamp": "1525699624",
    "formatted": "2018年5月7日 UTC 13:27:04"
  },
  "photoTakenTime": {
    "timestamp": "1525614892",
    "formatted": "2018年5月6日 UTC 13:54:52"
  },
  "geoData": {
    "latitude": 0.0,
    "longitude": 0.0,
    "altitude": 0.0,
    "latitudeSpan": 0.0,
    "longitudeSpan": 0.0
  },
  "geoDataExif": {
    "latitude": 0.0,
    "longitude": 0.0,
    "altitude": 0.0,
    "latitudeSpan": 0.0,
    "longitudeSpan": 0.0
  },
  "url": "https://lh3.googleusercontent.com/Ptv6pT7BQ23bjm1LGXN4odPmbvsswOhnQLDBcVy1Ku6Q8QvBcMJa-MVljAJRQ_YBz79t7TrKsxh3C7vrS85n2nA-DYpC7ZdQ8RyewG3H",
  "googlePhotosOrigin": {
    "mobileUpload": {
      "deviceFolder": {
        "localFolderName": ""
      },
      "deviceType": "ANDROID_PHONE"
    }
  }
}