{
  "title": "DSC_0079.JPG",
  "description": "",
  "imageViews": "12",
  "creationTime": {
    "timestamp": "1529057562",
    "formatted": "2018年6月15日 UTC 10:12:42"
  },
  "photoTakenTime": {
    "timestamp": "1527498583",
    "formatted": "2018年5月28日 UTC 09:09:43"
  },
  "geoData": {
    "latitude": 0.0,
    "longitude": 0.0,
    "altitude": 0.0,
    "latitudeSpan": 0.0,
    "longitudeSpan": 0.0
  },
  "geoDataExif": {
    "latitude": 0.0,
    "longitude": 0.0,
    "altitude": 0.0,
    "latitudeSpan": 0.0,
    "longitudeSpan": 0.0
  },
  "url": "https://lh3.googleusercontent.com/4aKgrZIqB4Dwh_rzVZkvMuekdwW-iig85eiHLZIgtk4aIxpGECHkTdFs0ey99molMjlqIguYqYjk-n4M8P3fxm0e9592ykwkcwSzUYet",
  "googlePhotosOrigin": {
    "mobileUpload": {
      "deviceFolder": {
        "localFolderName": ""
      },
      "deviceType": "ANDROID_PHONE"
    }
  }
}