{
  "fitnessActivity": "biking",
  "startTime": "2022-11-12T07:32:26.434Z",
  "endTime": "2022-11-12T08:37:20.282Z",
  "duration": "2271.838s",
  "segment": [{
    "fitnessActivity": "biking",
    "startTime": "2022-11-12T07:32:26.434Z",
    "endTime": "2022-11-12T07:49:13.167Z"
  }, {
    "fitnessActivity": "walking",
    "startTime": "2022-11-12T07:51:18.322Z",
    "endTime": "2022-11-12T07:53:49.536Z"
  }, {
    "fitnessActivity": "walking",
    "startTime": "2022-11-12T07:53:49.536Z",
    "endTime": "2022-11-12T07:56:02.815Z"
  }, {
    "fitnessActivity": "walking",
    "startTime": "2022-11-12T08:07:53.331Z",
    "endTime": "2022-11-12T08:09:15.756Z"
  }, {
    "fitnessActivity": "walking",
    "startTime": "2022-11-12T08:09:15.756Z",
    "endTime": "2022-11-12T08:09:16.057Z"
  }, {
    "fitnessActivity": "walking",
    "startTime": "2022-11-12T08:21:21.956Z",
    "endTime": "2022-11-12T08:22:09.419Z"
  }, {
    "fitnessActivity": "biking",
    "startTime": "2022-11-12T08:23:09.859Z",
    "endTime": "2022-11-12T08:37:20.282Z"
  }],
  "aggregate": [{
    "metricName": "com.google.heart_minutes.summary",
    "floatValue": 29.0
  }, {
    "metricName": "com.google.calories.expended",
    "floatValue": 200.96985373271266
  }, {
    "metricName": "com.google.step_count.delta",
    "intValue": 872
  }, {
    "metricName": "com.google.distance.delta",
    "floatValue": 533.2285981666596
  }, {
    "metricName": "com.google.speed.summary",
    "floatValue": 0.4693196684913983
  }, {
    "metricName": "com.google.active_minutes",
    "intValue": 47
  }]
}