{
  "title": "1448459844888.jpg",
  "description": "",
  "imageViews": "23",
  "creationTime": {
    "timestamp": "1451543388",
    "formatted": "2015年12月31日 UTC 06:29:48"
  },
  "photoTakenTime": {
    "timestamp": "1448459845",
    "formatted": "2015年11月25日 UTC 13:57:25"
  },
  "geoData": {
    "latitude": 0.0,
    "longitude": 0.0,
    "altitude": 0.0,
    "latitudeSpan": 0.0,
    "longitudeSpan": 0.0
  },
  "geoDataExif": {
    "latitude": 0.0,
    "longitude": 0.0,
    "altitude": 0.0,
    "latitudeSpan": 0.0,
    "longitudeSpan": 0.0
  },
  "url": "https://lh3.googleusercontent.com/1WwLN0XCJrUbg2gnQ_DEENdOAFrhgC4U4g5ez47ApSphKotOVbRaOiDIBKt8y3j-iXkMOoHXyymG75HcuxbW_C33E_oR1HVr5q61VIl6",
  "googlePhotosOrigin": {
    "photosDesktopUploader": {
    }
  }
}