{
  "fitnessActivity": "biking",
  "startTime": "2022-10-30T06:18:46.690Z",
  "endTime": "2022-10-30T06:34:57.841Z",
  "duration": "971.151s",
  "segment": [{
    "fitnessActivity": "biking",
    "startTime": "2022-10-30T06:18:46.690Z",
    "endTime": "2022-10-30T06:34:57.841Z"
  }],
  "aggregate": [{
    "metricName": "com.google.heart_minutes.summary",
    "floatValue": 15.0
  }, {
    "metricName": "com.google.calories.expended",
    "floatValue": 74.45491
  }, {
    "metricName": "com.google.active_minutes",
    "intValue": 15
  }]
}